folderikon/__init__.py
folderikon/__main__.py
folderikon/argparser.py
folderikon/constants.py
folderikon/exceptions.py
folderikon/folderikon.py
folderikon/notify_shell.py
folderikon-0.0.2.dist-info/LICENSE
folderikon-0.0.2.dist-info/METADATA
folderikon-0.0.2.dist-info/WHEEL
folderikon-0.0.2.dist-info/entry_points.txt
folderikon-0.0.2.dist-info/top_level.txt
folderikon-0.0.2.dist-info/RECORD
