Metadata-Version: 2.1
Name: folderikon
Version: 0.0.2
Summary: A Windows utility to set folder icons
Home-page: https://github.com/demberto/folderikon
Author: demberto
Author-email: demberto@protonmail.com
License: MIT
Project-URL: Bug Tracker, https://github.com/demberto/folderikon/issues
Project-URL: Changelog, https://github.com/demberto/folderikon/blob/master/CHANGELOG.md
Project-URL: TODO, https://github.com/demberto/folderikon/blob/master/TODO.md
Platform: UNKNOWN
Classifier: Development Status :: 4 - Beta
Classifier: Intended Audience :: End Users/Desktop
Classifier: License :: OSI Approved :: MIT License
Classifier: Natural Language :: English
Classifier: Operating System :: Microsoft :: Windows
Classifier: Programming Language :: Python
Classifier: Programming Language :: Python :: 3 :: Only
Classifier: Programming Language :: Python :: 3.6
Classifier: Programming Language :: Python :: 3.7
Classifier: Programming Language :: Python :: 3.8
Classifier: Programming Language :: Python :: 3.9
Classifier: Programming Language :: Python :: 3.10
Classifier: Topic :: Utilities
Requires-Python: >=3.6
License-File: LICENSE
Requires-Dist: Pillow (>=8.3.0)
Requires-Dist: colorama
Requires-Dist: requests
